{
  "id": "tw-d0050006",
  "type": "statute",
  "title": "國際間團體性之家庭兒童交換訪問辦法",
  "title_en": "國際間團體性之家庭兒童交換訪問辦法",
  "short_name": "國際間團體性之家庭兒童交換訪問辦法",
  "status": "repealed",
  "issued_date": "2021-06-29",
  "url": "https://law.moj.gov.tw/LawClass/LawAll.aspx?pcode=D0050006",
  "description": "Official legislation text from Taiwan Laws & Regulations Database. Category: 廢止法規＞內政部. Articles extracted: 9.",
  "provisions": [
    {
      "provision_ref": "art1",
      "section": "1",
      "title": "1",
      "content": "一、凡申請辦理國際間團體性家庭兒童交換訪問者，必須是已向政府立案登記之社團。"
    },
    {
      "provision_ref": "art2",
      "section": "2",
      "title": "2",
      "content": "二、必須具有詳細之交換計劃及正式邀請書，該項邀請書且須經我駐在地使領館之簽證。"
    },
    {
      "provision_ref": "art3",
      "section": "3",
      "title": "3",
      "content": "三、該項訪問僅限於會員之子女，且每戶每次不得超過一人。"
    },
    {
      "provision_ref": "art4",
      "section": "4",
      "title": "4",
      "content": "四、訪問兒童年齡，限於滿十歲至滿十五歲之間。"
    },
    {
      "provision_ref": "art5",
      "section": "5",
      "title": "5",
      "content": "五、訪問兒童須有領隊人員負責照料兒童之生活及安全，該領隊應以在團體中負有相關職務者為合格。"
    },
    {
      "provision_ref": "art6",
      "section": "6",
      "title": "6",
      "content": "六、申請訪問兒童及領隊人員，必須提具戶籍謄本、照片暨由主辦單位提出之出國保證書。"
    },
    {
      "provision_ref": "art7",
      "section": "7",
      "title": "7",
      "content": "七、訪問兒童及領隊人出國，概予發給團體護照，該項護照發給後不得要求延期及任何加簽。"
    },
    {
      "provision_ref": "art8",
      "section": "8",
      "title": "8",
      "content": "八、雙方交換訪問兒童之出境入境，主辦單位應事先報請內政部核可。"
    },
    {
      "provision_ref": "art9",
      "section": "9",
      "title": "9",
      "content": "九、交換期滿返國後，申請主辦單位應將往返日期及訪問情形書面報請內政部備查。"
    }
  ],
  "definitions": []
}
