{
  "id": "tw-d0060031",
  "type": "statute",
  "title": "實施航空測量攝影與遙感探測攝影作業規則",
  "title_en": "實施航空測量攝影與遙感探測攝影作業規則",
  "short_name": "實施航空測量攝影與遙感探測攝影作業規則",
  "status": "repealed",
  "issued_date": "2003-05-01",
  "url": "https://law.moj.gov.tw/LawClass/LawAll.aspx?pcode=D0060031",
  "description": "Official legislation text from Taiwan Laws & Regulations Database. Category: 廢止法規＞內政部. Articles extracted: 14.",
  "provisions": [
    {
      "provision_ref": "art1",
      "section": "1",
      "title": "第 1 條",
      "content": "為管理航空測量攝影 (以下簡稱航攝) 與遙感探測攝影 (以下簡\n稱遙攝) 作業，特訂定本規則。"
    },
    {
      "provision_ref": "art2",
      "section": "2",
      "title": "第 2 條",
      "content": "本規則所稱之航攝與遙攝作業，係指為供測量、製圖及判讀使用作業所需\n，以航空器攜帶攝影機或感測器對地面獲取影像資料之有關作業。"
    },
    {
      "provision_ref": "art3",
      "section": "3",
      "title": "第 3 條",
      "content": "有關航攝與遙攝作業原始影像資料之保管、曬製與供應業務應由內政部辦\n理之。\n前項業務內政部得委託有關機關辦理。"
    },
    {
      "provision_ref": "art4",
      "section": "4",
      "title": "第 4 條",
      "content": "政府機關依其組織法或組織規程之規定，有辦理航攝或遙攝之職掌且具備\n左列各款條件者，得申請辦理航攝或遙攝作業。但其情形特殊，經報請內\n政部核准者，不在此限。\n一、備有航攝或遙攝性能之航空器者。\n二、備有整套航攝或遙攝儀器及底片沖洗、曬印或影像處理設備者。\n三、置有航攝之飛行人員、領航人員或沖洗曬印人員者。"
    },
    {
      "provision_ref": "art5",
      "section": "5",
      "title": "第 5 條",
      "content": "航空公司或測量公司，合於左列各款規定者，得經內政部核准辦理航攝或\n遙攝作業。\n一、營業項目有航空測量或遙感探測者。\n二、公司負責人具有中華民國國籍者。\n三、備有航攝或遙攝性能之航空器者。\n四、備有整套航攝或遙攝儀器者。\n五、置有航攝之飛行人員或領航人員者。\n前項航空公司應具有普通航空業許可證者。"
    },
    {
      "provision_ref": "art6",
      "section": "6",
      "title": "第 6 條",
      "content": "政府機關、航空公司或測量公司 (以下簡稱辦理單位) 申請辦理或承攬航\n攝或遙攝作業時，應檢具左列文件向內政部申請：\n一、實施計畫書三份。\n二、航空公司或測量公司之公司執照及營利事業登記證影本。\n三、攝影地區範圍圖。\n四、辦理航攝或遙攝業務之設備清冊：\n (一) 飛機類型及機號。\n (二) 測量攝影儀器及沖洗曬印設備種類、名稱及架數。\n前項實施計畫書應載左列事項：\n一、目的。\n二、攝影地區及範圍。\n三、作業方法、攝影之航高、航速、比例尺、航線及重疊比、感測器種類\n    等。\n四、作業人員之姓名、年齡、住址、職務、身分證統一編號及登查號碼。\n五、經費概算表。\n六、實施期間。\n七、預計成果。\n八、民營航空公司及測量公司承攬之案件，應另附契約書。\n九、航攝或遙攝作業之影像資料如須送往國外處理者，應予敘明。\n十、其他有關事項。"
    },
    {
      "provision_ref": "art7",
      "section": "7",
      "title": "第 7 條",
      "content": "辦理單位應依內政部核定之航攝或遙攝作業實施計畫為之。\n違反前項規定者，得停止受理該辦理單位申請航攝或遙攝作業一年。"
    },
    {
      "provision_ref": "art8",
      "section": "8",
      "title": "第 8 條",
      "content": "內政部受理航攝或遙攝作業申請案件時，應會同國防部審核之。\n前項經內政部核准之申請案件，應副知交通部民用航空局及內政部警政署\n。"
    },
    {
      "provision_ref": "art9",
      "section": "9",
      "title": "第 9 條",
      "content": "實施航攝或遙攝作業之影像資料，其內容經沖洗或處理完成後，應訂定機\n密等級。\n前項之影像資料機密等級，由內政部會同國防部訂定之。\n航攝或遙攝影像資料之保密，應依國家機密保護辦法規定辦理。"
    },
    {
      "provision_ref": "art10",
      "section": "10",
      "title": "第 10 條",
      "content": "辦理單位於實施航攝或遙攝作業完竣後六十日內，應編製左列文件送內政\n部備查：\n一、工作報告書。\n二、航攝或遙攝之底片。\n三、攝影航線或影像資料涵蓋圖。\n前項工作報告書應含左列事項：\n一、實施計畫核准之文號。\n二、攝影地區範圍圖。\n三、成果統計。\n四、作業期程及概況說明。\n五、作業檢討。\n六、其他有關事項。\n違反前二項規定者，依第七條第二項規定辦理。"
    },
    {
      "provision_ref": "art11",
      "section": "11",
      "title": "第 11 條",
      "content": "需用已有航攝或遙攝地區影像資料者，向內政部申請製作，並繳納製作工\n本費。但該項資料屬機密者，由內政部轉國防部同意後辦理。\n前項有關資料製作工本費用，由內政部定之。"
    },
    {
      "provision_ref": "art12",
      "section": "12",
      "title": "第 12 條",
      "content": "第六條第一項第三款、第十條第二項第二款之攝影地區範圍圖與第十條第\n一項第三款之攝影航線或影像資料涵蓋圖均應以五萬分之一或十萬分之一\n地形圖為底圖描繪之。\n前項範圍圖或涵蓋圖之比例尺得視實際需要縮放之。"
    },
    {
      "provision_ref": "art13",
      "section": "13",
      "title": "第 13 條",
      "content": "本規則施行前各機關保管之有關航攝或遙攝原始影像資料，應清理列冊送\n內政部建檔。"
    },
    {
      "provision_ref": "art14",
      "section": "14",
      "title": "第 14 條",
      "content": "本規則自發布日施行。"
    }
  ],
  "definitions": []
}
