{
  "id": "tw-f0060005",
  "type": "statute",
  "title": "陸海空軍軍旗條例",
  "title_en": "Act of Ensign of the Armed Forces",
  "short_name": "Act of Ensign of the Armed Forces",
  "status": "in_force",
  "issued_date": "2022-05-18",
  "url": "https://law.moj.gov.tw/LawClass/LawAll.aspx?pcode=F0060005",
  "description": "Official legislation text from Taiwan Laws & Regulations Database. Category: 行政＞國防部＞服制旗章目. Articles extracted: 11.",
  "provisions": [
    {
      "provision_ref": "art1",
      "section": "1",
      "title": "第 1 條",
      "content": "陸海空軍軍旗，依本條例規定。"
    },
    {
      "provision_ref": "art2",
      "section": "2",
      "title": "第 2 條",
      "content": "軍旗種類如左\n一、統帥旗。\n二、軍事單位旗。\n三、官職旗。\n四、官階旗。\n五、海軍專用旗。"
    },
    {
      "provision_ref": "art3",
      "section": "3",
      "title": "第 3 條",
      "content": "統帥旗，為總統統率全國陸海空軍之旗。其旗式如附圖一。"
    },
    {
      "provision_ref": "art4",
      "section": "4",
      "title": "第 4 條",
      "content": "軍事單位旗，區分如下：\n一、國防部旗。\n二、陸軍旗。\n三、海軍旗。\n四、空軍旗。\n五、後備旗。\n六、憲兵旗。\n七、海軍陸戰隊旗。\n前項各款旗式，如附圖二。\n軍事單位旗，依前二項規定不足以表示機關、部隊、學校之特性時，得由國防部依實際需要定之。"
    },
    {
      "provision_ref": "art5",
      "section": "5",
      "title": "第 5 條",
      "content": "官職旗，區分如下：\n一、國防部部長旗。\n二、國防部參謀總長旗。\n三、國防部陸軍司令旗。\n四、國防部海軍司令旗。\n五、國防部空軍司令旗。\n六、國防部後備指揮官旗。\n前項第一款、第二款旗式，如附圖三。第三款至第六款旗式，由國防部定之。\n官職旗，依前二項規定不足以表示官職之特性時，得由國防部依實際需要定之。"
    },
    {
      "provision_ref": "art6",
      "section": "6",
      "title": "第 6 條",
      "content": "官階旗，為陸海空軍軍官官階識別之旗。其區分及旗式，由國防部定之。"
    },
    {
      "provision_ref": "art7",
      "section": "7",
      "title": "第 7 條",
      "content": "海軍專用旗，為海軍艦艇執行任務之旗。其區分如左：\n一、艦首旗。\n二、海軍資深軍官旗。\n三、海軍戰隊長旗。\n四、海軍海道測量艦艇桅旗。\n五、長旒。\n六、其他經國防部核定之專用旗。\n前項旗式，由國防部定之。"
    },
    {
      "provision_ref": "art8",
      "section": "8",
      "title": "第 8 條",
      "content": "統帥旗，由國防部製作。其他各種軍旗，由國防部統一製頒或授權製頒之。"
    },
    {
      "provision_ref": "art9",
      "section": "9",
      "title": "第 9 條",
      "content": "本條例所定各種軍旗之圖說及使用、懸掛、持行之規定，由國防部定之。"
    },
    {
      "provision_ref": "art10",
      "section": "10",
      "title": "第 10 條",
      "content": "本條例施行細則，由國防部定之。"
    },
    {
      "provision_ref": "art11",
      "section": "11",
      "title": "第 11 條",
      "content": "本條例自公布日施行。"
    }
  ],
  "definitions": []
}
