{
  "id": "tw-h0020065",
  "type": "statute",
  "title": "國立新竹生活美學館場地使用規費收費標準",
  "title_en": "國立新竹生活美學館場地使用規費收費標準",
  "short_name": "國立新竹生活美學館場地使用規費收費標準",
  "status": "repealed",
  "issued_date": "2014-11-14",
  "url": "https://law.moj.gov.tw/LawClass/LawAll.aspx?pcode=H0020065",
  "description": "Official legislation text from Taiwan Laws & Regulations Database. Category: 廢止法規＞文化部. Articles extracted: 4.",
  "provisions": [
    {
      "provision_ref": "art1",
      "section": "1",
      "title": "第 1 條",
      "content": "本標準依規費法第十條第一項規定訂定之。"
    },
    {
      "provision_ref": "art2",
      "section": "2",
      "title": "第 2 條",
      "content": "本館研習教室場地使用規費如下：\n一、一零三、一零九、二零二、二零三教室每場使用費用新臺幣一千九百\n    元。\n二、一零四、二零五教室每場使用費用新臺幣二千四百元。\n不使用冷氣時每場減收新臺幣三百元，使用時段及收費標準如附表。"
    },
    {
      "provision_ref": "art3",
      "section": "3",
      "title": "第 3 條",
      "content": "前條收費基準，視物價、市場行情變動或成本變動，每三年至少應辦理檢\n討一次。"
    },
    {
      "provision_ref": "art4",
      "section": "4",
      "title": "第 4 條",
      "content": "本標準自發布日施行。"
    }
  ],
  "definitions": []
}
