{
  "id": "tw-j0080042",
  "type": "statute",
  "title": "企業併購償還積欠銀行債務免徵營利事業所得稅辦法",
  "title_en": "企業併購償還積欠銀行債務免徵營利事業所得稅辦法",
  "short_name": "企業併購償還積欠銀行債務免徵營利事業所得稅辦法",
  "status": "repealed",
  "issued_date": "2011-01-28",
  "url": "https://law.moj.gov.tw/LawClass/LawAll.aspx?pcode=J0080042",
  "description": "Official legislation text from Taiwan Laws & Regulations Database. Category: 廢止法規＞經濟部. Articles extracted: 6.",
  "provisions": [
    {
      "provision_ref": "art1",
      "section": "1",
      "title": "第 1 條",
      "content": "本辦法依企業併購法 (以下簡稱本法) 第三十七條第五項規定訂定之。"
    },
    {
      "provision_ref": "art2",
      "section": "2",
      "title": "第 2 條",
      "content": "本辦法用詞定義如下：\n一、虧損公司：指截至併購基準日止之累積盈餘為負數之公司。\n二、有盈餘公司：指虧損公司以外之其他公司。\n三、銀行：指商業銀行、專業銀行、信託投資公司、信用合作社、農會信\n    用部、漁會信用部、票券金融公司及其他經財政部核准辦理授信貸款\n    業務者。\n四、積欠銀行之債務：指公司截至併購基準日止，向銀行之借款已逾清償\n    期而未償還之債務。\n五、免稅所得額：指併購之財產或營業部分產生之所得，依本辦法規定計\n    算免徵營利事業所得稅之金額。"
    },
    {
      "provision_ref": "art3",
      "section": "3",
      "title": "第 3 條",
      "content": "有盈餘公司併購虧損公司，或虧損公司互為合併，償還併購時隨同移轉積\n欠銀行之債務，得自併購基準日起，就併購之財產或營業部分產生之所得\n，五年內免徵營利事業所得稅。但每一年度之免稅所得額，以不超過截至\n當年度止實際償還積欠銀行債務之累積總額扣除截至上年度止免稅所得額\n累計數後之餘額為限。"
    },
    {
      "provision_ref": "art4",
      "section": "4",
      "title": "第 4 條",
      "content": "適用免徵營利事業所得稅之公司，就併購之營業或財產應單獨設立帳簿，\n正確計算免稅所得額；其計算免稅所得額時，應合理分攤相關管理費用及\n非營業損益。\n公司依前項規定單獨設立帳簿計算免稅所得額有困難者，得於會計年度終\n了後二個月內，由其營利事業所得稅查核簽證申報會計師敘明理由，並提\n出合理計算公式，報經財政部核准後採用之；其所提計算公式一經採用，\n不得變更。"
    },
    {
      "provision_ref": "art5",
      "section": "5",
      "title": "第 5 條",
      "content": "符合免徵營利事業所得稅規定之公司，應於辦理營利事業所得稅結算申報\n時，檢附下列文件，向所在地稅捐稽徵機關申辦免稅：\n一、併購契約或計畫。\n二、符合第二條第一款、第二款規定之相關文件及說明。\n三、債權銀行出具符合第二條第四款規定之證明文件。"
    },
    {
      "provision_ref": "art6",
      "section": "6",
      "title": "第 6 條",
      "content": "本辦法自中華民國九十一年二月八日施行至九十六年二月八日止。"
    }
  ],
  "definitions": [
    {
      "term": "虧損公司",
      "definition": "指截至併購基準日止之累積盈餘為負數之公司。",
      "source_provision": "art2"
    },
    {
      "term": "有盈餘公司",
      "definition": "指虧損公司以外之其他公司。",
      "source_provision": "art2"
    },
    {
      "term": "銀行",
      "definition": "指商業銀行、專業銀行、信託投資公司、信用合作社、農會信 用部、漁會信用部、票券金融公司及其他經財政部核准辦理授信貸款 業務者。",
      "source_provision": "art2"
    },
    {
      "term": "積欠銀行之債務",
      "definition": "指公司截至併購基準日止，向銀行之借款已逾清償 期而未償還之債務。",
      "source_provision": "art2"
    },
    {
      "term": "免稅所得額",
      "definition": "指併購之財產或營業部分產生之所得，依本辦法規定計 算免徵營利事業所得稅之金額。",
      "source_provision": "art2"
    }
  ]
}
