{
  "id": "tw-j0120039",
  "type": "statute",
  "title": "漢翔航空工業股份有限公司董事會及監察人設置辦法",
  "title_en": "漢翔航空工業股份有限公司董事會及監察人設置辦法",
  "short_name": "漢翔航空工業股份有限公司董事會及監察人設置辦法",
  "status": "repealed",
  "issued_date": "2017-08-08",
  "url": "https://law.moj.gov.tw/LawClass/LawAll.aspx?pcode=J0120039",
  "description": "Official legislation text from Taiwan Laws & Regulations Database. Category: 廢止法規＞經濟部. Articles extracted: 9.",
  "provisions": [
    {
      "provision_ref": "art1",
      "section": "1",
      "title": "第 1 條",
      "content": "本辦法係依漢翔航空工業股份有限公司 (以下簡稱本公司) 設置條例第四\n條第三項規定訂定之。"
    },
    {
      "provision_ref": "art2",
      "section": "2",
      "title": "第 2 條",
      "content": "本辦法未規定者，悉依經濟部其他相關法令辦理。"
    },
    {
      "provision_ref": "art3",
      "section": "3",
      "title": "第 3 條",
      "content": "本公司董事會置董事九人至十五人；置常務董事三人至五人，由董事互選\n之；常務董事互選一人為董事長，並由經濟部報請行政院核定。"
    },
    {
      "provision_ref": "art4",
      "section": "4",
      "title": "第 4 條",
      "content": "本公司置監察人三人至五人，並互選一人為常務監察人，由經濟部核定。"
    },
    {
      "provision_ref": "art5",
      "section": "5",
      "title": "第 5 條",
      "content": "本公司董事及監察人之任期為三年，並得連選連任。"
    },
    {
      "provision_ref": "art6",
      "section": "6",
      "title": "第 6 條",
      "content": "本公司董事及監察人之遴派，依經濟部所屬各公司董事監察人遴派標準辦\n理。"
    },
    {
      "provision_ref": "art7",
      "section": "7",
      "title": "第 7 條",
      "content": "監察人除依法執行其職務外，並得列席董事會陳述其意見，但不參加表決\n。"
    },
    {
      "provision_ref": "art8",
      "section": "8",
      "title": "第 8 條",
      "content": "本公司董事會原則每季開會一次。但有緊急情事時，得隨時召集之。"
    },
    {
      "provision_ref": "art9",
      "section": "9",
      "title": "第 9 條",
      "content": "本辦法自發布日施行。"
    }
  ],
  "definitions": []
}
