{
  "id": "tw-k0000105",
  "type": "statute",
  "title": "交通部花蓮港務局棧埠管理處暫行組織規程",
  "title_en": "交通部花蓮港務局棧埠管理處暫行組織規程",
  "short_name": "交通部花蓮港務局棧埠管理處暫行組織規程",
  "status": "repealed",
  "issued_date": "2003-01-10",
  "url": "https://law.moj.gov.tw/LawClass/LawAll.aspx?pcode=K0000105",
  "description": "Official legislation text from Taiwan Laws & Regulations Database. Category: 廢止法規＞交通部. Articles extracted: 10.",
  "provisions": [
    {
      "provision_ref": "art1",
      "section": "1",
      "title": "第 1 條",
      "content": "本規程依臺灣省政府功能業務與組織調整暫行條例第五條第二項及花蓮港\n務局暫行組織規程第十二條規定訂定之。"
    },
    {
      "provision_ref": "art2",
      "section": "2",
      "title": "第 2 條",
      "content": "本處設二股，分別掌理下列事項：\n一、搬運股：碼頭工人出勤、調派、技術指導、效率統計事項。\n二、倉儲股：倉位分配、貨物提存、簽證事項。"
    },
    {
      "provision_ref": "art3",
      "section": "3",
      "title": "第 3 條",
      "content": "本處置處長一人，承花蓮港務局局長之命，綜理處務；副處長一人，襄理\n之。"
    },
    {
      "provision_ref": "art4",
      "section": "4",
      "title": "第 4 條",
      "content": "本處設機具保養場，置主任一人 (技術人員兼任) ，掌理機具之調配、保\n養及效率考核事項。"
    },
    {
      "provision_ref": "art5",
      "section": "5",
      "title": "第 5 條",
      "content": "本處置稽查、幫工程司、股長、技士、倉庫管理員、股員、辦事員、倉庫\n副管理員、技佐、書記、領班、技術工、業務工等各若干人，其員額另以\n暫行編制表定之。"
    },
    {
      "provision_ref": "art6",
      "section": "6",
      "title": "第 6 條",
      "content": "本處人事、會計及政風事項由花蓮港務局人事室、會計室及政風室派員駐\n處辦理。"
    },
    {
      "provision_ref": "art7",
      "section": "7",
      "title": "第 7 條",
      "content": "本處各倉庫區，各置倉庫主任一人，掌理貨物儲存、裝卸事項。"
    },
    {
      "provision_ref": "art8",
      "section": "8",
      "title": "第 8 條",
      "content": "本規程所列各職稱之資位，另依交通事業人員資位職務薪給表之規定辦理\n。"
    },
    {
      "provision_ref": "art9",
      "section": "9",
      "title": "第 9 條",
      "content": "本處分層負責明細表，由本處訂定，報花蓮港務局備查。\n\n┌──────────────────────────────┐\n│交通部花蓮港務局棧埠管理處暫行編制表 (核定本)               │\n├────────┬───┬─────────────────┤\n│職  務  名  稱  │員  額│備                              註│\n├────────┼───┼─────────────────┤\n│處長            │一    │                                  │\n├────────┼───┼─────────────────┤\n│副處長          │一    │以上為高員級以上人員。            │\n├────────┼───┼─────────────────┤\n│稽查            │一    │                                  │\n├────────┼───┼─────────────────┤\n│幫工程司        │一    │                                  │\n├────────┼───┼─────────────────┤\n│股長            │二    │                                  │\n├────────┼───┼─────────────────┤\n│機具保養場主任  │ (一) │由技術人員兼任。                  │\n├────────┼───┼─────────────────┤\n│技士            │二    │                                  │\n├────────┼───┼─────────────────┤\n│倉庫主任        │三    │                                  │\n├────────┼───┼─────────────────┤\n│倉庫管理員      │一五  │以上為員級跨高員級人員。          │\n├─┬──────┼───┼─────────────────┤\n│員│業務類      │一一  │                                  │\n│級├──────┼───┼─────────────────┤\n│  │技術類      │二    │                                  │\n├─┼──────┼───┼─────────────────┤\n│佐│業務類      │二    │                                  │\n│級├──────┼───┼─────────────────┤\n│  │技術類      │○    │                                  │\n├─┼──────┼───┼─────────────────┤\n│士│業務類      │二二  │                                  │\n│級├──────┼───┼─────────────────┤\n│  │技術類      │一八  │                                  │\n├─┴──────┼───┼─────────────────┤\n│合            計│八一  │                                  │\n│                │ (一) │                                  │\n├────────┴───┴─────────────────┤\n│附註：本編制表自中華民國八十八年七月一日施行。              │\n└──────────────────────────────┘"
    },
    {
      "provision_ref": "art10",
      "section": "10",
      "title": "第 10 條",
      "content": "本規程自中華民國八十八年七月一日施行。"
    }
  ],
  "definitions": []
}
