{
  "id": "tw-o0060030",
  "type": "statute",
  "title": "環境用藥標示準則",
  "title_en": "環境用藥標示準則",
  "short_name": "環境用藥標示準則",
  "status": "in_force",
  "issued_date": "2006-07-24",
  "url": "https://law.moj.gov.tw/LawClass/LawAll.aspx?pcode=O0060030",
  "description": "Official legislation text from Taiwan Laws & Regulations Database. Category: 行政＞環境部＞化學物質管理目. Articles extracted: 8.",
  "provisions": [
    {
      "provision_ref": "art1",
      "section": "1",
      "title": "第 1 條",
      "content": "本準則依環境用藥管理法（以下簡稱本法）第二十七條第二項規定訂定之。"
    },
    {
      "provision_ref": "art2",
      "section": "2",
      "title": "第 2 條",
      "content": "環境用藥之標示文字，應以中文為之，必要時得輔以外文，其項目如下：\n一、環境用藥字樣。\n二、警示圖案或警語。\n三、許可證字號。\n四、品名。\n五、有效成分及含量。\n六、性能。\n七、劑型及內容量。\n八、適用範圍及使用方法。\n九、使用及儲藏時應注意事項。\n十、中毒症狀、急救及解毒方法。\n十一、廢容器回收清理方式。\n十二、廠商名稱、地址及電話號碼。\n十三、製造日期及批號。\n十四、產品有效期限。\n前項第十二款所稱廠商，指製造廠商或輸入廠商；輸入之環境用藥應加註原製造廠國別、名稱及地址。"
    },
    {
      "provision_ref": "art3",
      "section": "3",
      "title": "第 3 條",
      "content": "前條第一項第一款所稱環境用藥字樣如下：\n一、一般環境衛生用藥、特殊環境衛生用藥或環境衛生用藥原體。\n二、污染防治用藥。\n三、一般環境用藥微生物製劑、特殊環境用藥微生物製劑或環境用藥微生物製劑原體。"
    },
    {
      "provision_ref": "art4",
      "section": "4",
      "title": "第 4 條",
      "content": "第二條第一項第二款所稱警示圖案或警語，依環境衛生用藥、環境用藥微生物製劑原體之毒性及產品特性分類，標示警示圖案或顏色，如附件。\n污染防治用藥標示警示圖案或警語，參照聯合國化學品標示規定。"
    },
    {
      "provision_ref": "art5",
      "section": "5",
      "title": "第 5 條",
      "content": "下列環境用藥標示之變更，應自核准變更後，其製造或輸入應即使用變更後之標示內容，不得使用庫存之原標示：\n一、品名。\n二、性能。\n三、廠商名稱、地址。\n前項規定以外之變更標示，有庫存原標示者，於核准變更後六個月內仍得使用。"
    },
    {
      "provision_ref": "art6",
      "section": "6",
      "title": "第 6 條",
      "content": "第二條規定項目以外之文字或圖案，不得有下列情形之一：\n一、與核准標示內容不符。\n二、誇大虛偽不實。\n三、有致消費者誤信之虞。\n四、違背公共秩序或善良風俗。"
    },
    {
      "provision_ref": "art7",
      "section": "7",
      "title": "第 7 條",
      "content": "申請變更下列環境用藥標示內容，應檢具標示及佐證資料；輸入之環境用藥應另檢具出產國商品化之標示：\n一、警示圖案或警語。\n二、適用範圍及使用方法。\n三、使用及儲藏時應注意事項。\n四、中毒症狀、急救及解毒方法。\n廢容器回收清理方式之標示變更，依廢容器回收清除處理規定辦理。\n前二項以外之其他標示變更，應於變更環境用藥許可證時併同為之。"
    },
    {
      "provision_ref": "art8",
      "section": "8",
      "title": "第 8 條",
      "content": "本準則自發布日施行。"
    }
  ],
  "definitions": []
}
