{
  "id": "tw-r0030081",
  "type": "statute",
  "title": "特種考試監察院監察調查人員考試規則",
  "title_en": "特種考試監察院監察調查人員考試規則",
  "short_name": "特種考試監察院監察調查人員考試規則",
  "status": "repealed",
  "issued_date": "2002-10-11",
  "url": "https://law.moj.gov.tw/LawClass/LawAll.aspx?pcode=R0030081",
  "description": "Official legislation text from Taiwan Laws & Regulations Database. Category: 廢止法規＞考選部. Articles extracted: 16.",
  "provisions": [
    {
      "provision_ref": "art1",
      "section": "1",
      "title": "第 1 條",
      "content": "本規則依公務人員考試法施行細則第四條規定訂定之。"
    },
    {
      "provision_ref": "art2",
      "section": "2",
      "title": "第 2 條",
      "content": "特種考試監察院監察調查人員考試 (以下簡稱本考試) 分一等考試、二等\n考試、三等考試。\n前項一等考試相當於高等考試一級考試，二等考試相當於高等考試二級考\n試，三等考試相當於高等考試三級考試。"
    },
    {
      "provision_ref": "art3",
      "section": "3",
      "title": "第 3 條",
      "content": "中華民國國民，年齡在十八歲以上，四十五歲以下，具有下列各款資格之\n一者，得應本考試一等考試：\n一、公立或立案之私立大學研究院、所或經教育部承認之國外大學研究院\n    、所畢業得有博士學位證書者。\n二、公務人員高等考試二級考試或相當高等考試二級考試及格者。"
    },
    {
      "provision_ref": "art4",
      "section": "4",
      "title": "第 4 條",
      "content": "中華民國國民，年齡在十八歲以上，四十歲以下，具有下列各款資格之一\n者，得應本考試二等考試：\n一、公立或立案之私立大學研究院、所或經教育部承認之國外大學研究院\n    、所畢業得有碩士學位證書者。\n二、公務人員高等考試三級考試或相當高等考試三級考試及格者。"
    },
    {
      "provision_ref": "art5",
      "section": "5",
      "title": "第 5 條",
      "content": "中華民國國民，年齡在十八歲以上，四十歲以下，具有下列各款資格之一\n者，得應本考試三等考試：\n一、公立或立案之私立專科以上學校或經教育部承認之國外專科以上學校\n    畢業得有證書者。\n二、普通考試或相當普通考試之特種考試及格者。\n三、高等檢定考試及格者。"
    },
    {
      "provision_ref": "art6",
      "section": "6",
      "title": "第 6 條",
      "content": "本考試之男性應考人須服畢兵役或核准免服兵役或現正服役中，法定役期\n尚未屆滿者。"
    },
    {
      "provision_ref": "art7",
      "section": "7",
      "title": "第 7 條",
      "content": "本考試分筆試及口試，筆試未錄取者不得參加口試。"
    },
    {
      "provision_ref": "art8",
      "section": "8",
      "title": "第 8 條",
      "content": "本考試各等別之類科及應試科目依附表之規定。"
    },
    {
      "provision_ref": "art9",
      "section": "9",
      "title": "第 9 條",
      "content": "本考試應考人於筆試錄取後，應經試務機關指定之醫療機構辦理體格檢查\n，體格檢查不合格或未於規定期間內繳交體格檢查表者，不得參加口試。\n前項體格檢查標準，依公務人員考試體格檢查標準之規定辦理。"
    },
    {
      "provision_ref": "art10",
      "section": "10",
      "title": "第 10 條",
      "content": "本考試以筆試成績占百分之八十，口試成績占百分二十，合併計算為考試\n總成績後，配合任用需求擇優錄取。\n筆試成績之計算，一等考試以各科目成績平均計算之；二、三等考試以普\n通科目成績加專業科目成績合併計算之，普通科目成績以每科成績乘以百\n分之十後之總和計算之，專業科目成績以各科目成績總和除以科目數再乘\n以所占剩餘百分比計算之。\n前項筆試成績有一科為零分或專業科目平均成績不滿五十分，或三等考試\n建築工程類科之「建築設計」成績不滿五十分，或口試成績不滿六十分者\n，均不予錄取。缺考之科目，以零分計算。"
    },
    {
      "provision_ref": "art11",
      "section": "11",
      "title": "第 11 條",
      "content": "本考試錄取人員，須經訓練，訓練期滿成績及格，送由公務人員保障暨培\n訓委員會核定，始完成考試程序，報請考試院發給考試及格證書，並由監\n察院任用。\n前項訓練，依公務人員考試錄取人員訓練辦法之規定辦理。"
    },
    {
      "provision_ref": "art12",
      "section": "12",
      "title": "第 12 條",
      "content": "本考試及格人員，取得同職組各職系之任用資格，並不得轉調監察院暨其\n所屬以外機關任職。\n前項不得轉調之限制應於考試及格證書註明，並函請銓敘部查照。"
    },
    {
      "provision_ref": "art13",
      "section": "13",
      "title": "第 13 條",
      "content": "本考試組織典試委員會，主持典試事宜，其試務由考選部辦理。"
    },
    {
      "provision_ref": "art14",
      "section": "14",
      "title": "第 14 條",
      "content": "本考試辦理竣事，考選部應將辦理典試及試務情形，連同關係文件一併報\n請考試院核備。"
    },
    {
      "provision_ref": "art15",
      "section": "15",
      "title": "第 15 條",
      "content": "本規則未規定事項，適用一般考試法規之規定。"
    },
    {
      "provision_ref": "art16",
      "section": "16",
      "title": "第 16 條",
      "content": "本規則自發布日施行。"
    }
  ],
  "definitions": []
}
